sanic_amqp_ext/__init__.py
sanic_amqp_extension-0.1.2.dist-info/METADATA
sanic_amqp_extension-0.1.2.dist-info/RECORD
sanic_amqp_extension-0.1.2.dist-info/WHEEL
sanic_amqp_extension-0.1.2.dist-info/top_level.txt
