Metadata-Version: 2.1
Name: sanic-amqp-extension
Version: 0.1.2
Summary: AMQP support for Sanic framework
Home-page: https://github.com/Relrin/sanic-amqp-extension
Author: Valeryi Savich
Author-email: relrin78@gmail.com
License: BSD
Platform: any
Classifier: Environment :: Web Environment
Classifier: License :: OSI Approved :: BSD License
Classifier: Intended Audience :: Developers
Classifier: Programming Language :: Python
Classifier: Programming Language :: Python :: 3
Classifier: Programming Language :: Python :: 3.5
Classifier: Programming Language :: Python :: 3.6
Classifier: Programming Language :: Python :: 3.7
Classifier: Topic :: Software Development :: Libraries :: Python Modules
Requires-Dist: sanic-base-extension (==0.1.1)
Requires-Dist: aioamqp (==0.12.0)
